email_monitor/__init__.py
email_monitor/exceptions.py
email_monitor/main.py
email_monitor-0.1.0.dist-info/LICENSE
email_monitor-0.1.0.dist-info/METADATA
email_monitor-0.1.0.dist-info/WHEEL
email_monitor-0.1.0.dist-info/top_level.txt
email_monitor-0.1.0.dist-info/RECORD
