Metadata-Version: 2.1
Name: email-monitor
Version: 0.1.0
Summary: A versatile IMAP mail monitoring module with Gmail API support, regex queries, and flexible search options
Home-page: https://github.com/glizzykingdreko/email_monitor
Author: glizzykingdreko
Author-email: glizzykingdreko@protonmail.com
Classifier: Development Status :: 3 - Alpha
Classifier: Intended Audience :: Developers
Classifier: License :: OSI Approved :: MIT License
Classifier: Operating System :: OS Independent
Classifier: Programming Language :: Python :: 3
Classifier: Programming Language :: Python :: 3.8
Classifier: Programming Language :: Python :: 3.9
Requires-Python: >=3.8
License-File: LICENSE
Requires-Dist: google-auth-oauthlib
Requires-Dist: google-auth-httplib2
Requires-Dist: google-api-python-client
